fp-3D/hdl/in_triangle.sv
`timescale 1ns / 1ps
`default_nettype none

/*
Given two positive integer pixel locations a, b, return the corresponding vector ab
*/
module p2v_wrap #(
    parameter SYS_BIT_WIDTH = 32
) (
    input wire [SYS_BIT_WIDTH-1:0] point_ax,
    input wire [SYS_BIT_WIDTH-1:0] point_ay,
    input wire [SYS_BIT_WIDTH-1:0] point_bx,
    input wire [SYS_BIT_WIDTH-1:0] point_by,
    output logic signed [SYS_BIT_WIDTH:0] vec_ab_out_x,
    output logic signed [SYS_BIT_WIDTH:0] vec_ab_out_y
);
    always_comb begin 
        vec_ab_out_x = point_bx - point_ax;
        vec_ab_out_y = point_by - point_ay; 
    end
    
endmodule

/*
Given two 2d vectors with integer coordinates, return the corresponding cross product
*/
module cp_helper_wrap #(
    parameter SYS_BIT_WIDTH = 32
) (
    input wire clk_in,
    input wire valid_in,
    input wire [SYS_BIT_WIDTH:0] vec_ax,
    input wire [SYS_BIT_WIDTH:0] vec_ay,
    input wire [SYS_BIT_WIDTH:0] vec_bx,
    input wire [SYS_BIT_WIDTH:0] vec_by,
    output logic valid_out,
    output logic signed [SYS_BIT_WIDTH+SYS_BIT_WIDTH:0] value_out
);
    logic signed [SYS_BIT_WIDTH:0] vec_a [1:0];
    logic signed [SYS_BIT_WIDTH:0] vec_b [1:0];
    logic signed [SYS_BIT_WIDTH+SYS_BIT_WIDTH:0] multiples [1:0]; 
    //might need one more bit here if substrend is negative while number is positive or vice versa
    logic state;

    always_comb begin 
        vec_a[0] = vec_ax;
        vec_a[1] = vec_ay;
        vec_b[0] = vec_bx;
        vec_b[1] = vec_by;
    end

    always_ff @( posedge clk_in ) begin
        if (valid_out) begin
            valid_out <= 0;
        end

        if (valid_in) begin
            multiples[0] <= vec_a[0] * vec_b[1];
            multiples[1] <= vec_a[1] * vec_b[0];
            state <= 1;
        end else if (state == 1) begin
            valid_out <= 1;
            value_out <= multiples[0] - multiples[1];
            state <= 0;
        end

    end
endmodule


module in_triangle #(
    parameter SYS_BIT_WIDTH = 32
) (
    input wire clk_in,
    input wire valid_in,
    input wire [SYS_BIT_WIDTH-1:0] vertex_a [1:0],
    input wire [SYS_BIT_WIDTH-1:0] vertex_b [1:0],
    input wire [SYS_BIT_WIDTH-1:0] vertex_c [1:0],
    input wire [SYS_BIT_WIDTH-1:0] point [1:0],
    output logic valid_out,
    output logic is_inside
);
    logic signed [SYS_BIT_WIDTH:0] vec_AB [1:0];
    logic signed [SYS_BIT_WIDTH:0] vec_AC [1:0];
    logic signed [SYS_BIT_WIDTH:0] vec_PA [1:0];
    logic signed [SYS_BIT_WIDTH:0] vec_PB [1:0];
    logic signed [SYS_BIT_WIDTH:0] vec_PC [1:0];

    logic signed [SYS_BIT_WIDTH+SYS_BIT_WIDTH:0] ka_constant;
    logic signed [SYS_BIT_WIDTH+SYS_BIT_WIDTH:0] kb_constant;
    logic signed [SYS_BIT_WIDTH+SYS_BIT_WIDTH:0] d_constant;

    // Calculate vectors AB and AC
    p2v_wrap #(.SYS_BIT_WIDTH(SYS_BIT_WIDTH)) ab (
        .point_ax(vertex_a[0]),
        .point_ay(vertex_a[1]),
        .point_bx(vertex_b[0]),
        .point_by(vertex_b[1]),
        .vec_ab_out_x(vec_AB[0]),
        .vec_ab_out_y(vec_AB[1])
    );

    p2v_wrap #(.SYS_BIT_WIDTH(SYS_BIT_WIDTH)) ac (
        .point_ax(vertex_a[0]),
        .point_ay(vertex_a[1]),
        .point_bx(vertex_c[0]),
        .point_by(vertex_c[1]),
        .vec_ab_out_x(vec_AC[0]),
        .vec_ab_out_y(vec_AC[1])
    );

    p2v_wrap #(.SYS_BIT_WIDTH(SYS_BIT_WIDTH)) pa (
        .point_ax(point[0]),
        .point_ay(point[1]),
        .point_bx(vertex_a[0]),
        .point_by(vertex_a[1]),
        .vec_ab_out_x(vec_PA[0]),
        .vec_ab_out_y(vec_PA[1])
    );

    p2v_wrap #(.SYS_BIT_WIDTH(SYS_BIT_WIDTH)) pb (
        .point_ax(point[0]),
        .point_ay(point[1]),
        .point_bx(vertex_b[0]),
        .point_by(vertex_b[1]),
        .vec_ab_out_x(vec_PB[0]),
        .vec_ab_out_y(vec_PB[1])
    );

    p2v_wrap #(.SYS_BIT_WIDTH(SYS_BIT_WIDTH)) pc (
        .point_ax(point[0]),
        .point_ay(point[1]),
        .point_bx(vertex_c[0]),
        .point_by(vertex_c[1]),
        .vec_ab_out_x(vec_PC[0]),
        .vec_ab_out_y(vec_PC[1])
    );

    // Calculate ka = ||PB X PC||
    logic ka_valid;
    cp_helper_wrap #(.SYS_BIT_WIDTH(SYS_BIT_WIDTH)) ka (
        .clk_in(clk_in),
        .valid_in(valid_in),
        .vec_ax(vec_PB[0]),
        .vec_ay(vec_PB[1]),
        .vec_bx(vec_PC[0]),
        .vec_by(vec_PC[1]),
        .valid_out(ka_valid),
        .value_out(ka_constant)
    );

    // Calculate kb = ||PC X PA||
    logic kb_valid;
    cp_helper_wrap #(.SYS_BIT_WIDTH(SYS_BIT_WIDTH)) kb (
        .clk_in(clk_in),
        .valid_in(valid_in),
        .vec_ax(vec_PC[0]),
        .vec_ay(vec_PC[1]),
        .vec_bx(vec_PA[0]),
        .vec_by(vec_PA[1]),
        .valid_out(kb_valid),
        .value_out(kb_constant)
    );

    // Calculate d = ||AB X AC||
    logic d_valid;
    cp_helper_wrap #(.SYS_BIT_WIDTH(SYS_BIT_WIDTH)) d (
        .clk_in(clk_in),
        .valid_in(valid_in),
        .vec_ax(vec_AB[0]),
        .vec_ay(vec_AB[1]),
        .vec_bx(vec_AC[0]),
        .vec_by(vec_AC[1]),
        .valid_out(d_valid),
        .value_out(d_constant)
    );

    logic pos_a;
    logic pos_b;

    logic signed [SYS_BIT_WIDTH+SYS_BIT_WIDTH:0] d_abs;
    logic signed [SYS_BIT_WIDTH+SYS_BIT_WIDTH+1:0] f_constant;
    logic [SYS_BIT_WIDTH+SYS_BIT_WIDTH+1:0] f_abs;
    logic f_valid;
    logic signed [SYS_BIT_WIDTH+SYS_BIT_WIDTH+2:0] c_check;
    logic c_check_valid;

    logic complete;


    localparam sign_idx = SYS_BIT_WIDTH + SYS_BIT_WIDTH;
    always_comb begin
        pos_a = (ka_constant[sign_idx] == d_constant[sign_idx]) || (ka_constant == 0);
        pos_b = (kb_constant[sign_idx] == d_constant[sign_idx]) || (kb_constant == 0);
        f_abs = f_constant[sign_idx+1] == 1 ?  0 - f_constant : f_constant;
        d_abs = d_constant[sign_idx] == 1 ?  0 - d_constant : d_constant;
    end

    always_ff @(posedge clk_in ) begin

        if (valid_out) begin
            valid_out <= 0;
        end

        if (valid_in) begin // is this a valid condition?
            complete <= 0;
            valid_out <= 0;
        end

        if (ka_valid && kb_valid && d_valid) begin
            if (!pos_a || !pos_b) begin
                valid_out <= 1;
                is_inside <= 0;
                complete <= 1;
            end else begin
                f_constant <= ka_constant + kb_constant;
                f_valid <= 1;
            end

        end else if (f_valid) begin
            if (f_constant == d_constant) begin
                valid_out <= 1;
                is_inside <= 1;
                complete <= 1;
            end else begin // d - f (subtraction not being done correctly) - fixed
                if (!f_constant[sign_idx+1] && d_constant[sign_idx]) begin
                    c_check <= 0 - (d_abs + f_abs);
                end else if (!f_constant[sign_idx+1] && d_constant[sign_idx]) begin
                    c_check <= f_abs + d_abs;
                end else begin
                    c_check <= d_constant - f_constant;
                end
                c_check_valid <= 1;
                f_valid <= 0;
            end
        end else if (c_check_valid) begin
            is_inside <= c_check[sign_idx+2] == d_constant[sign_idx];
            valid_out <= 1;
            complete <= 1;
        end
    end
endmodule

module in_triangle_wrap #(
    parameter SYS_BIT_WIDTH = 32
) (
    input wire clk_in,
    input wire valid_in,
    input wire [SYS_BIT_WIDTH-1:0] vertex_ax,
    input wire [SYS_BIT_WIDTH-1:0] vertex_ay,
    input wire [SYS_BIT_WIDTH-1:0] vertex_bx,
    input wire [SYS_BIT_WIDTH-1:0] vertex_by,
    input wire [SYS_BIT_WIDTH-1:0] vertex_cx,
    input wire [SYS_BIT_WIDTH-1:0] vertex_cy,
    input wire [SYS_BIT_WIDTH-1:0] point_x,
    input wire [SYS_BIT_WIDTH-1:0] point_y,
    output logic valid_out,
    output logic is_inside
);
    logic [SYS_BIT_WIDTH-1:0] vertex_a [1:0];
    logic [SYS_BIT_WIDTH-1:0] vertex_b [1:0];
    logic [SYS_BIT_WIDTH-1:0] vertex_c [1:0];
    logic [SYS_BIT_WIDTH-1:0] point [1:0];

    always_comb begin 
        vertex_a[0] = vertex_ax;
        vertex_a[1] = vertex_ay;
        vertex_b[0] = vertex_bx;
        vertex_b[1] = vertex_by;
        vertex_c[0] = vertex_cx;
        vertex_c[1] = vertex_cy;
        point[0] = point_x;
        point[1] = point_y;
    end

    in_triangle #(.SYS_BIT_WIDTH(SYS_BIT_WIDTH)) triangle (
        .clk_in(clk_in),
        .valid_in(valid_in),
        .vertex_a(vertex_a),
        .vertex_b(vertex_b),
        .vertex_c(vertex_c),
        .point(point),
        .valid_out(valid_out),
        .is_inside(is_inside)
    );

endmodule

fp-3D/sim/triangle_tb.sv
`timescale 1ns / 1ps
`default_nettype none

module triangle_tb();
    logic [5:0] vertex_ax;
    logic [5:0] vertex_ay;
    logic [5:0] vertex_bx;
    logic [5:0] vertex_by;
    logic [5:0] vertex_cx;
    logic [5:0] vertex_cy; 
    logic [5:0] point_x;
    logic [5:0] point_y; 

    logic data_valid_in;
    logic data_valid_out;
    logic is_inside;

    logic clk_in;

    
    in_triangle_wrap #(.SYS_BIT_WIDTH(6)) uut (
        .clk_in(clk_in),
        .valid_in(data_valid_in),
        .vertex_ax(vertex_ax),
        .vertex_ay(vertex_ay),
        .vertex_bx(vertex_bx),
        .vertex_by(vertex_by),
        .vertex_cx(vertex_cx),
        .vertex_cy(vertex_cy),
        .point_x(point_x),
        .point_y(point_y),
        .valid_out(data_valid_out),
        .is_inside(is_inside)
    );

    always begin
      #5;  //every 5 ns switch...so period of clock is 10 ns...100 MHz clock
      clk_in = !clk_in;
    end

    initial begin
      $dumpfile("triangle.vcd"); //file to store value change dump (vcd)
      $dumpvars(0,triangle_tb);
      $display("Starting Sim"); 
      clk_in = 0;
      #10;
      vertex_ax = 'd0;
      vertex_ay = 'd0;
      vertex_bx = 'd10;
      vertex_by = 'd30;
      vertex_cx = 'd20;
      vertex_cy = 'd0;
      point_x = 'd10;
      point_y = 'd15;
      data_valid_in = 1;
      #10;
      data_valid_in = 0;
      #1000;
      $finish;
    end
endmodule
`default_nettype wire

fp-3D/sim/output/triangle.vcd
$date
	Wed Dec  6 16:37:27 2023
$end
$version
	Icarus Verilog
$end
$timescale
	1ps
$end
$scope module triangle_tb $end
$var wire 1 ! is_inside $end
$var wire 1 " data_valid_out $end
$var reg 1 # clk_in $end
$var reg 1 $ data_valid_in $end
$var reg 6 % point_x [5:0] $end
$var reg 6 & point_y [5:0] $end
$var reg 6 ' vertex_ax [5:0] $end
$var reg 6 ( vertex_ay [5:0] $end
$var reg 6 ) vertex_bx [5:0] $end
$var reg 6 * vertex_by [5:0] $end
$var reg 6 + vertex_cx [5:0] $end
$var reg 6 , vertex_cy [5:0] $end
$scope module uut $end
$var wire 1 # clk_in $end
$var wire 6 - point_x [5:0] $end
$var wire 6 . point_y [5:0] $end
$var wire 1 $ valid_in $end
$var wire 6 / vertex_ax [5:0] $end
$var wire 6 0 vertex_ay [5:0] $end
$var wire 6 1 vertex_bx [5:0] $end
$var wire 6 2 vertex_by [5:0] $end
$var wire 6 3 vertex_cx [5:0] $end
$var wire 6 4 vertex_cy [5:0] $end
$var wire 1 " valid_out $end
$var wire 1 ! is_inside $end
$var parameter 32 5 SYS_BIT_WIDTH $end
$scope module triangle $end
$var wire 1 # clk_in $end
$var wire 1 $ valid_in $end
$var wire 1 6 kb_valid $end
$var wire 13 7 kb_constant [12:0] $end
$var wire 1 8 ka_valid $end
$var wire 13 9 ka_constant [12:0] $end
$var wire 1 : d_valid $end
$var wire 13 ; d_constant [12:0] $end
$var parameter 32 < SYS_BIT_WIDTH $end
$var parameter 33 = sign_idx $end
$var reg 15 > c_check [14:0] $end
$var reg 1 ? c_check_valid $end
$var reg 1 @ complete $end
$var reg 13 A d_abs [12:0] $end
$var reg 14 B f_abs [13:0] $end
$var reg 14 C f_constant [13:0] $end
$var reg 1 D f_valid $end
$var reg 1 ! is_inside $end
$var reg 1 E pos_a $end
$var reg 1 F pos_b $end
$var reg 1 " valid_out $end
$scope module ab $end
$var wire 6 G point_ax [5:0] $end
$var wire 6 H point_ay [5:0] $end
$var wire 6 I point_bx [5:0] $end
$var wire 6 J point_by [5:0] $end
$var parameter 32 K SYS_BIT_WIDTH $end
$var reg 7 L vec_ab_out_x [6:0] $end
$var reg 7 M vec_ab_out_y [6:0] $end
$upscope $end
$scope module ac $end
$var wire 6 N point_ax [5:0] $end
$var wire 6 O point_ay [5:0] $end
$var wire 6 P point_bx [5:0] $end
$var wire 6 Q point_by [5:0] $end
$var parameter 32 R SYS_BIT_WIDTH $end
$var reg 7 S vec_ab_out_x [6:0] $end
$var reg 7 T vec_ab_out_y [6:0] $end
$upscope $end
$scope module d $end
$var wire 1 # clk_in $end
$var wire 1 $ valid_in $end
$var wire 7 U vec_ax [6:0] $end
$var wire 7 V vec_ay [6:0] $end
$var wire 7 W vec_bx [6:0] $end
$var wire 7 X vec_by [6:0] $end
$var parameter 32 Y SYS_BIT_WIDTH $end
$var reg 1 Z state $end
$var reg 1 : valid_out $end
$var reg 13 [ value_out [12:0] $end
$upscope $end
$scope module ka $end
$var wire 1 # clk_in $end
$var wire 1 $ valid_in $end
$var wire 7 \ vec_by [6:0] $end
$var wire 7 ] vec_bx [6:0] $end
$var wire 7 ^ vec_ay [6:0] $end
$var wire 7 _ vec_ax [6:0] $end
$var parameter 32 ` SYS_BIT_WIDTH $end
$var reg 1 a state $end
$var reg 1 8 valid_out $end
$var reg 13 b value_out [12:0] $end
$upscope $end
$scope module kb $end
$var wire 1 # clk_in $end
$var wire 1 $ valid_in $end
$var wire 7 c vec_by [6:0] $end
$var wire 7 d vec_bx [6:0] $end
$var wire 7 e vec_ay [6:0] $end
$var wire 7 f vec_ax [6:0] $end
$var parameter 32 g SYS_BIT_WIDTH $end
$var reg 1 h state $end
$var reg 1 6 valid_out $end
$var reg 13 i value_out [12:0] $end
$upscope $end
$scope module pa $end
$var wire 6 j point_ax [5:0] $end
$var wire 6 k point_ay [5:0] $end
$var wire 6 l point_bx [5:0] $end
$var wire 6 m point_by [5:0] $end
$var parameter 32 n SYS_BIT_WIDTH $end
$var reg 7 o vec_ab_out_x [6:0] $end
$var reg 7 p vec_ab_out_y [6:0] $end
$upscope $end
$scope module pb $end
$var wire 6 q point_ax [5:0] $end
$var wire 6 r point_ay [5:0] $end
$var wire 6 s point_bx [5:0] $end
$var wire 6 t point_by [5:0] $end
$var parameter 32 u SYS_BIT_WIDTH $end
$var reg 7 v vec_ab_out_x [6:0] $end
$var reg 7 w vec_ab_out_y [6:0] $end
$upscope $end
$scope module pc $end
$var wire 6 x point_ax [5:0] $end
$var wire 6 y point_ay [5:0] $end
$var wire 6 z point_bx [5:0] $end
$var wire 6 { point_by [5:0] $end
$var parameter 32 | SYS_BIT_WIDTH $end
$var reg 7 } vec_ab_out_x [6:0] $end
$var reg 7 ~ vec_ab_out_y [6:0] $end
$upscope $end
$upscope $end
$upscope $end
$upscope $end
$enddefinitions $end
$comment Show the parameter values. $end
$dumpall
b110 |
b110 u
b110 n
b110 g
b110 `
b110 Y
b110 R
b110 K
b1100 =
b110 <
b110 5
$end
#0
$dumpvars
bx ~
bx }
bx {
bx z
bx y
bx x
bx w
bx v
bx t
bx s
bx r
bx q
bx p
bx o
bx m
bx l
bx k
bx j
bx i
xh
bx f
bx e
bx d
bx c
bx b
xa
bx _
bx ^
bx ]
bx \
bx [
xZ
bx X
bx W
bx V
bx U
bx T
bx S
bx Q
bx P
bx O
bx N
bx M
bx L
bx J
bx I
bx H
bx G
xF
xE
xD
bx C
bx B
bx A
x@
x?
bx >
bx ;
x:
bx 9
x8
bx 7
x6
bx 4
bx 3
bx 2
bx 1
bx 0
bx /
bx .
bx -
bx ,
bx +
bx *
bx )
bx (
bx '
bx &
bx %
x$
0#
x"
x!
$end
#5000
1#
#10000
b1110001 \
b1110001 e
b1110001 ~
b1010 ]
b1010 f
b1010 }
b1111 ^
b1111 w
b0 _
b0 v
b11110 M
b11110 V
b1010 L
b1010 U
b0 T
b0 X
b10100 S
b10100 W
b1110001 c
b1110001 p
b1110110 d
b1110110 o
b1111 k
b1111 r
b1111 y
b1010 j
b1010 q
b1010 x
b0 Q
b0 {
b10100 P
b10100 z
b11110 J
b11110 t
b1010 I
b1010 s
b0 H
b0 O
b0 m
b0 G
b0 N
b0 l
0#
1$
b1111 &
b1111 .
b1010 %
b1010 -
b0 ,
b0 4
b10100 +
b10100 3
b11110 *
b11110 2
b1010 )
b1010 1
b0 (
b0 0
b0 '
b0 /
#15000
0"
0@
1Z
1h
1a
1#
#20000
0#
0$
#25000
b1001011000 A
1F
1E
0a
b1111101101010 9
b1111101101010 b
18
0h
b1111011010100 7
b1111011010100 i
16
0Z
b1110110101000 ;
b1110110101000 [
1:
1#
#30000
0#
#35000
b111000010 B
1D
b11111000111110 C
0:
06
08
1#
#40000
0#
#45000
0D
1?
b111111101101010 >
1#
#50000
0#
#55000
1@
1"
1!
0?
1#
#60000
0#
#65000
0"
1#
