game_project/hdl/tmds_encoder.sv
module tm_choice (
  input wire [7:0] data_in,
  output logic [8:0] qm_out
  );


  logic [$clog2(8):0] sum_of_digits;
  
  assign sum_of_digits = data_in[0] + data_in[1] + data_in[2] + data_in[3] + data_in[4] + data_in[5] + data_in[6] + data_in[7];

  always_comb begin 
    if ( (sum_of_digits > 4) || ( (sum_of_digits == 4) && (data_in[0] == 0) ) ) begin //option 2
      qm_out[8] = 0;
      qm_out[0] = data_in[0];
      qm_out[1] = ~(~data_in[1] == qm_out[0]);
      qm_out[2] = ~(~data_in[2] == qm_out[1]);
      qm_out[3] = ~(~data_in[3] == qm_out[2]);
      qm_out[4] = ~(~data_in[4] == qm_out[3]);
      qm_out[5] = ~(~data_in[5] == qm_out[4]);
      qm_out[6] = ~(~data_in[6] == qm_out[5]);
      qm_out[7] = ~(~data_in[7] == qm_out[6]);
      
    end else begin //option 1
      qm_out[8] = 1;
      qm_out[0] = data_in[0];
      qm_out[1] = (~data_in[1] == qm_out[0]);
      qm_out[2] = (~data_in[2] == qm_out[1]);
      qm_out[3] = (~data_in[3] == qm_out[2]);
      qm_out[4] = (~data_in[4] == qm_out[3]);
      qm_out[5] = (~data_in[5] == qm_out[4]);
      qm_out[6] = (~data_in[6] == qm_out[5]);
      qm_out[7] = (~data_in[7] == qm_out[6]);
      
    end
  end 

endmodule //end tm_choice



module tmds_encoder(
  input wire clk_in,
  input wire rst_in,
  input wire [7:0] data_in,  // video data (red, green or blue)
  input wire [1:0] control_in, //for blue set to {vs,hs}, else will be 0
  input wire ve_in,  // video data enable, to choose between control or video signal
  output logic [9:0] tmds_out
);

  logic [8:0] q_m;
  logic [4:0] tally;
  //you can assume a functioning (version of tm_choice for you.)
  tm_choice mtm(
    .data_in(data_in),
    .qm_out(q_m));

  //your code here.
  logic [$clog2(10):0] q_m_sum;
  assign q_m_sum = q_m[0] + q_m[1] + q_m[2] + q_m[3] + q_m[4] + q_m[5] + q_m[6] + q_m[7];


always_ff @(posedge clk_in) begin

        if (rst_in) begin
            tmds_out <= 0;
            tally <= 0;
        end else begin
            if (ve_in) begin
                if ( (tally == 0) || (q_m_sum == 4)) begin //triangle 1 true
             
                    tmds_out[9] <= !q_m[8];
                    tmds_out[8] <= q_m[8];
                    //tmds_out[7:0] <= (q_m[8])? q_m[7:0]: (~q_m[7:0]);
                    if (q_m[8]) begin
                        tmds_out[7:0] <= q_m[7:0];
                    end else begin
                        tmds_out[7:0] <= ~q_m[7:0];
                    end

                    if (q_m[8] == 0) begin //triangle 2 true
                        tally <= tally + 8 - q_m_sum - q_m_sum; 
                    end else begin //triangle 2 false
                        tally <= tally + q_m_sum - (8- q_m_sum);
                    end 
                  

                end else begin //triangle 1 false
       
                    if ( ((tally[4] == 0) && (q_m_sum > 4)) || ((tally[4] == 1) && (q_m_sum < 4))) begin //triangle 3 true
                        tmds_out[9] <= 1;
                        tmds_out[8] <= q_m[8];
                        tmds_out[7:0] <= ~q_m[7:0];
                        tally <= tally + q_m[8] + q_m[8] + (8 - q_m_sum) - q_m_sum;
                      
                    end else begin //triangle 3 false
                        tmds_out[9] <= 0;
                        tmds_out[8] <= q_m[8];
                        tmds_out[7:0] <= q_m[7:0];
                        tally <= tally - !q_m[8] - !q_m[8] + q_m_sum + q_m_sum - 8;
                    end

                end 
            end else begin
                tally <= 0;
                if (control_in == 2'b00) begin
                    tmds_out <= 10'b1101010100;
                end else if (control_in == 2'b01) begin
                    tmds_out <= 10'b0010101011;
                end else if (control_in == 2'b10) begin
                    tmds_out <= 10'b0101010100;
                end else if (control_in == 2'b11) begin
                    tmds_out <= 10'b1010101011;
                end
            end
        end
end

endmodule //end tmds_encoder

game_project/sim/tmds_2_tb.sv

`timescale 1ns / 1ps
`default_nettype none


module tmds_2_tb();

  logic clk_in;
  logic rst_in;
	logic [7:0] data_in;
	logic [1:0] control_in;
	logic ve_in;
	logic [9:0] tmds_out;
  tmds_encoder uut(
  .clk_in(clk_in),
  .rst_in(rst_in),
  .data_in(data_in),  // video data (red, green or blue)
  .control_in(control_in),  // control data
  .ve_in(ve_in),  // video data enable, to choose between CD (when VDE=0) and VD (when VDE=1)
  .tmds_out(tmds_out)
  );

  always begin
      #5;  //every 5 ns switch...so period of clock is 10 ns...100 MHz clock
      clk_in = !clk_in;
  end
  //initial block...this is our test simulation
  initial begin
    $dumpfile("tmds_2_tb.vcd"); //file to store value change dump (vcd)
    $dumpvars(0,tmds_2_tb);
    $display("Starting Sim"); //print nice message at start
    clk_in = 0;
    rst_in = 1;
    control_in = 0;
    ve_in = 1;
    data_in = 0;;
    #10;
    rst_in=0;
    for(int i = 0; i<1024; i = i+1)begin
      data_in = i;
      #10;
    end
    control_in = 0;
    #100;
    control_in = 1;
    #100;
    control_in = 2;
    #100;
    control_in = 3;
    #100;
    ve_in = 0;
    control_in = 0;
    #100;
    control_in = 1;
    #100;
    control_in = 2;
    #100;
    control_in = 3;
    #100;
    ve_in = 1;
    #10;
    for(int i = 0; i<1024; i = i+1)begin
      data_in = 255-i;
      #10;
    end
    #500;
    $display("Finishing Sim"); //print nice message at end
    $finish;
  end
endmodule
`default_nettype wire

game_project/tmds_2_tb.vcd
$date
	Wed Oct  4 21:32:19 2023
$end
$version
	Icarus Verilog
$end
$timescale
	1ps
$end
$scope module tmds_2_tb $end
$var wire 10 ! tmds_out [9:0] $end
$var reg 1 " clk_in $end
$var reg 2 # control_in [1:0] $end
$var reg 8 $ data_in [7:0] $end
$var reg 1 % rst_in $end
$var reg 1 & ve_in $end
$scope module uut $end
$var wire 1 " clk_in $end
$var wire 2 ' control_in [1:0] $end
$var wire 8 ( data_in [7:0] $end
$var wire 1 % rst_in $end
$var wire 1 & ve_in $end
$var wire 5 ) q_m_sum [4:0] $end
$var wire 9 * q_m [8:0] $end
$var reg 5 + tally [4:0] $end
$var reg 10 , tmds_out [9:0] $end
$scope module mtm $end
$var wire 8 - data_in [7:0] $end
$var wire 4 . sum_of_digits [3:0] $end
$var reg 9 / qm_out [8:0] $end
$upscope $end
$upscope $end
$scope begin $ivl_for_loop0 $end
$var integer 32 0 i [31:0] $end
$upscope $end
$scope begin $ivl_for_loop1 $end
$var integer 32 1 i [31:0] $end
$upscope $end
$upscope $end
$enddefinitions $end
$comment Show the parameter values. $end
$dumpall
$end
#0
$dumpvars
b0 1
b0 0
b100000000 /
b0 .
b0 -
bx ,
bx +
b100000000 *
b0 )
b0 (
b0 '
1&
1%
b0 $
b0 #
0"
bx !
$end
#5000
b0 +
b0 !
b0 ,
1"
#10000
0"
0%
#15000
b11000 +
b100000000 !
b100000000 ,
1"
#20000
b1000 )
b111111111 *
b111111111 /
b1 .
0"
b1 $
b1 (
b1 -
b1 0
#25000
b0 +
b111111111 !
b111111111 ,
1"
#30000
b111 )
b111111110 *
b111111110 /
b1 .
0"
b10 $
b10 (
b10 -
b10 0
#35000
b110 +
b111111110 !
b111111110 ,
1"
#40000
b1 )
b100000001 *
b100000001 /
b10 .
0"
b11 $
b11 (
b11 -
b11 0
#45000
b0 +
b100000001 !
b100000001 ,
1"
#50000
b110 )
b111111100 *
b111111100 /
b1 .
0"
b100 $
b100 (
b100 -
b100 0
#55000
b100 +
b111111100 !
b111111100 ,
1"
#60000
b10 )
b100000011 *
b100000011 /
b10 .
0"
b101 $
b101 (
b101 -
b101 0
#65000
b0 +
b100000011 !
b100000011 ,
1"
#70000
b1 )
b100000010 *
b100000010 /
b10 .
0"
b110 $
b110 (
b110 -
b110 0
#75000
b11010 +
b100000010 !
b100000010 ,
1"
#80000
b111 )
b111111101 *
b111111101 /
b11 .
0"
b111 $
b111 (
b111 -
b111 0
#85000
b0 +
b111111101 !
b111111101 ,
1"
#90000
b101 )
b111111000 *
b111111000 /
b1 .
0"
b1000 $
b1000 (
b1000 -
b1000 0
#95000
b10 +
b111111000 !
b111111000 ,
1"
#100000
b11 )
b100000111 *
b100000111 /
b10 .
0"
b1001 $
b1001 (
b1001 -
b1001 0
#105000
b0 +
b100000111 !
b100000111 ,
1"
#110000
b10 )
b100000110 *
b100000110 /
b10 .
0"
b1010 $
b1010 (
b1010 -
b1010 0
#115000
b11100 +
b100000110 !
b100000110 ,
1"
#120000
b110 )
b111111001 *
b111111001 /
b11 .
0"
b1011 $
b1011 (
b1011 -
b1011 0
#125000
b0 +
b111111001 !
b111111001 ,
1"
#130000
b1 )
b100000100 *
b100000100 /
b10 .
0"
b1100 $
b1100 (
b1100 -
b1100 0
#135000
b11010 +
b100000100 !
b100000100 ,
1"
#140000
b111 )
b111111011 *
b111111011 /
b11 .
0"
b1101 $
b1101 (
b1101 -
b1101 0
#145000
b0 +
b111111011 !
b111111011 ,
1"
#150000
b110 )
b111111010 *
b111111010 /
b11 .
0"
b1110 $
b1110 (
b1110 -
b1110 0
#155000
b100 +
b111111010 !
b111111010 ,
1"
#160000
b10 )
b100000101 *
b100000101 /
b100 .
0"
b1111 $
b1111 (
b1111 -
b1111 0
#165000
b0 +
b100000101 !
b100000101 ,
1"
#170000
b100 )
b111110000 *
b111110000 /
b1 .
0"
b10000 $
b10000 (
b10000 -
b10000 0
#175000
b111110000 !
b111110000 ,
1"
#180000
b100 )
b100001111 *
b100001111 /
b10 .
0"
b10001 $
b10001 (
b10001 -
b10001 0
#185000
b100001111 !
b100001111 ,
1"
#190000
b11 )
b100001110 *
b100001110 /
b10 .
0"
b10010 $
b10010 (
b10010 -
b10010 0
#195000
b11110 +
b100001110 !
b100001110 ,
1"
#200000
b101 )
b111110001 *
b111110001 /
b11 .
0"
b10011 $
b10011 (
b10011 -
b10011 0
#205000
b0 +
b111110001 !
b111110001 ,
1"
#210000
b10 )
b100001100 *
b100001100 /
b10 .
0"
b10100 $
b10100 (
b10100 -
b10100 0
#215000
b11100 +
b100001100 !
b100001100 ,
1"
#220000
b110 )
b111110011 *
b111110011 /
b11 .
0"
b10101 $
b10101 (
b10101 -
b10101 0
#225000
b0 +
b111110011 !
b111110011 ,
1"
#230000
b101 )
b111110010 *
b111110010 /
b11 .
0"
b10110 $
b10110 (
b10110 -
b10110 0
#235000
b10 +
b111110010 !
b111110010 ,
1"
#240000
b11 )
b100001101 *
b100001101 /
b100 .
0"
b10111 $
b10111 (
b10111 -
b10111 0
#245000
b0 +
b100001101 !
b100001101 ,
1"
#250000
b1 )
b100001000 *
b100001000 /
b10 .
0"
b11000 $
b11000 (
b11000 -
b11000 0
#255000
b11010 +
b100001000 !
b100001000 ,
1"
#260000
b111 )
b111110111 *
b111110111 /
b11 .
0"
b11001 $
b11001 (
b11001 -
b11001 0
#265000
b0 +
b111110111 !
b111110111 ,
1"
#270000
b110 )
b111110110 *
b111110110 /
b11 .
0"
b11010 $
b11010 (
b11010 -
b11010 0
#275000
b100 +
b111110110 !
b111110110 ,
1"
#280000
b10 )
b100001001 *
b100001001 /
b100 .
0"
b11011 $
b11011 (
b11011 -
b11011 0
#285000
b0 +
b100001001 !
b100001001 ,
1"
#290000
b101 )
b111110100 *
b111110100 /
b11 .
0"
b11100 $
b11100 (
b11100 -
b11100 0
#295000
b10 +
b111110100 !
b111110100 ,
1"
#300000
b11 )
b100001011 *
b100001011 /
b100 .
0"
b11101 $
b11101 (
b11101 -
b11101 0
#305000
b0 +
b100001011 !
b100001011 ,
1"
#310000
b10 )
b10100000 *
b10100000 /
b100 .
0"
b11110 $
b11110 (
b11110 -
b11110 0
#315000
b100 +
b1001011111 !
b1001011111 ,
1"
#320000
b110 )
b1011111 *
b1011111 /
b101 .
0"
b11111 $
b11111 (
b11111 -
b11111 0
#325000
b0 +
b1010100000 !
b1010100000 ,
1"
#330000
b11 )
b111100000 *
b111100000 /
b1 .
0"
b100000 $
b100000 (
b100000 -
b100000 0
#335000
b11110 +
b111100000 !
b111100000 ,
1"
#340000
b101 )
b100011111 *
b100011111 /
b10 .
0"
b100001 $
b100001 (
b100001 -
b100001 0
#345000
b0 +
b100011111 !
b100011111 ,
1"
#350000
b100 )
b100011110 *
b100011110 /
b10 .
0"
b100010 $
b100010 (
b100010 -
b100010 0
#355000
b100011110 !
b100011110 ,
1"
#360000
b100 )
b111100001 *
b111100001 /
b11 .
0"
b100011 $
b100011 (
b100011 -
b100011 0
#365000
b111100001 !
b111100001 ,
1"
#370000
b11 )
b100011100 *
b100011100 /
b10 .
0"
b100100 $
b100100 (
b100100 -
b100100 0
#375000
b11110 +
b100011100 !
b100011100 ,
1"
#380000
b101 )
b111100011 *
b111100011 /
b11 .
0"
b100101 $
b100101 (
b100101 -
b100101 0
#385000
b0 +
b111100011 !
b111100011 ,
1"
#390000
b100 )
b111100010 *
b111100010 /
b11 .
0"
b100110 $
b100110 (
b100110 -
b100110 0
#395000
b111100010 !
b111100010 ,
1"
#400000
b100 )
b100011101 *
b100011101 /
b100 .
0"
b100111 $
b100111 (
b100111 -
b100111 0
#405000
b100011101 !
b100011101 ,
1"
#410000
b10 )
b100011000 *
b100011000 /
b10 .
0"
b101000 $
b101000 (
b101000 -
b101000 0
#415000
b11100 +
b100011000 !
b100011000 ,
1"
#420000
b110 )
b111100111 *
b111100111 /
b11 .
0"
b101001 $
b101001 (
b101001 -
b101001 0
#425000
b0 +
b111100111 !
b111100111 ,
1"
#430000
b101 )
b111100110 *
b111100110 /
b11 .
0"
b101010 $
b101010 (
b101010 -
b101010 0
#435000
b10 +
b111100110 !
b111100110 ,
1"
#440000
b11 )
b100011001 *
b100011001 /
b100 .
0"
b101011 $
b101011 (
b101011 -
b101011 0
#445000
b0 +
b100011001 !
b100011001 ,
1"
#450000
b100 )
b111100100 *
b111100100 /
b11 .
0"
b101100 $
b101100 (
b101100 -
b101100 0
#455000
b111100100 !
b111100100 ,
1"
#460000
b100 )
b100011011 *
b100011011 /
b100 .
0"
b101101 $
b101101 (
b101101 -
b101101 0
#465000
b100011011 !
b100011011 ,
1"
#470000
b11 )
b10110000 *
b10110000 /
b100 .
0"
b101110 $
b101110 (
b101110 -
b101110 0
#475000
b10 +
b1001001111 !
b1001001111 ,
1"
#480000
b101 )
b1001111 *
b1001111 /
b101 .
0"
b101111 $
b101111 (
b101111 -
b101111 0
#485000
b0 +
b1010110000 !
b1010110000 ,
1"
#490000
b1 )
b100010000 *
b100010000 /
b10 .
0"
b110000 $
b110000 (
b110000 -
b110000 0
#495000
b11010 +
b100010000 !
b100010000 ,
1"
#500000
b111 )
b111101111 *
b111101111 /
b11 .
0"
b110001 $
b110001 (
b110001 -
b110001 0
#505000
b0 +
b111101111 !
b111101111 ,
1"
#510000
b110 )
b111101110 *
b111101110 /
b11 .
0"
b110010 $
b110010 (
b110010 -
b110010 0
#515000
b100 +
b111101110 !
b111101110 ,
1"
#520000
b10 )
b100010001 *
b100010001 /
b100 .
0"
b110011 $
b110011 (
b110011 -
b110011 0
#525000
b0 +
b100010001 !
b100010001 ,
1"
#530000
b101 )
b111101100 *
b111101100 /
b11 .
0"
b110100 $
b110100 (
b110100 -
b110100 0
#535000
b10 +
b111101100 !
b111101100 ,
1"
#540000
b11 )
b100010011 *
b100010011 /
b100 .
0"
b110101 $
b110101 (
b110101 -
b110101 0
#545000
b0 +
b100010011 !
b100010011 ,
1"
#550000
b100 )
b10111000 *
b10111000 /
b100 .
0"
b110110 $
b110110 (
b110110 -
b110110 0
#555000
b1001000111 !
b1001000111 ,
1"
#560000
b100 )
b1000111 *
b1000111 /
b101 .
0"
b110111 $
b110111 (
b110111 -
b110111 0
#565000
b1010111000 !
b1010111000 ,
1"
#570000
b100 )
b111101000 *
b111101000 /
b11 .
0"
b111000 $
b111000 (
b111000 -
b111000 0
#575000
b111101000 !
b111101000 ,
1"
#580000
b100 )
b100010111 *
b100010111 /
b100 .
0"
b111001 $
b111001 (
b111001 -
b111001 0
#585000
b100010111 !
b100010111 ,
1"
#590000
b101 )
b10111100 *
b10111100 /
b100 .
0"
b111010 $
b111010 (
b111010 -
b111010 0
#595000
b11110 +
b1001000011 !
b1001000011 ,
1"
#600000
b11 )
b1000011 *
b1000011 /
b101 .
0"
b111011 $
b111011 (
b111011 -
b111011 0
#605000
b0 +
b1010111100 !
b1010111100 ,
1"
#610000
b110 )
b10111110 *
b10111110 /
b100 .
0"
b111100 $
b111100 (
b111100 -
b111100 0
#615000
b11100 +
b1001000001 !
b1001000001 ,
1"
#620000
b10 )
b1000001 *
b1000001 /
b101 .
0"
b111101 $
b111101 (
b111101 -
b111101 0
#625000
b0 +
b1010111110 !
b1010111110 ,
1"
#630000
b1 )
b1000000 *
b1000000 /
b101 .
0"
b111110 $
b111110 (
b111110 -
b111110 0
#635000
b110 +
b1010111111 !
b1010111111 ,
1"
#640000
b111 )
b10111111 *
b10111111 /
b110 .
0"
b111111 $
b111111 (
b111111 -
b111111 0
#645000
b0 +
b1001000000 !
b1001000000 ,
1"
#650000
b10 )
b111000000 *
b111000000 /
b1 .
0"
b1000000 $
b1000000 (
b1000000 -
b1000000 0
#655000
b11100 +
b111000000 !
b111000000 ,
1"
#660000
b110 )
b100111111 *
b100111111 /
b10 .
0"
b1000001 $
b1000001 (
b1000001 -
b1000001 0
#665000
b0 +
b100111111 !
b100111111 ,
1"
#670000
b101 )
b100111110 *
b100111110 /
b10 .
0"
b1000010 $
b1000010 (
b1000010 -
b1000010 0
#675000
b10 +
b100111110 !
b100111110 ,
1"
#680000
b11 )
b111000001 *
b111000001 /
b11 .
0"
b1000011 $
b1000011 (
b1000011 -
b1000011 0
#685000
b0 +
b111000001 !
b111000001 ,
1"
#690000
b100 )
b100111100 *
b100111100 /
b10 .
0"
b1000100 $
b1000100 (
b1000100 -
b1000100 0
#695000
b100111100 !
b100111100 ,
1"
#700000
b100 )
b111000011 *
b111000011 /
b11 .
0"
b1000101 $
b1000101 (
b1000101 -
b1000101 0
#705000
b111000011 !
b111000011 ,
1"
#710000
b11 )
b111000010 *
b111000010 /
b11 .
0"
b1000110 $
b1000110 (
b1000110 -
b1000110 0
#715000
b11110 +
b111000010 !
b111000010 ,
1"
#720000
b101 )
b100111101 *
b100111101 /
b100 .
0"
b1000111 $
b1000111 (
b1000111 -
b1000111 0
#725000
b0 +
b100111101 !
b100111101 ,
1"
#730000
b11 )
b100111000 *
b100111000 /
b10 .
0"
b1001000 $
b1001000 (
b1001000 -
b1001000 0
#735000
b11110 +
b100111000 !
b100111000 ,
1"
#740000
b101 )
b111000111 *
b111000111 /
b11 .
0"
b1001001 $
b1001001 (
b1001001 -
b1001001 0
#745000
b0 +
b111000111 !
b111000111 ,
1"
#750000
b100 )
b111000110 *
b111000110 /
b11 .
0"
b1001010 $
b1001010 (
b1001010 -
b1001010 0
#755000
b111000110 !
b111000110 ,
1"
#760000
b100 )
b100111001 *
b100111001 /
b100 .
0"
b1001011 $
b1001011 (
b1001011 -
b1001011 0
#765000
b100111001 !
b100111001 ,
1"
#770000
b11 )
b111000100 *
b111000100 /
b11 .
0"
b1001100 $
b1001100 (
b1001100 -
b1001100 0
#775000
b11110 +
b111000100 !
b111000100 ,
1"
#780000
b101 )
b100111011 *
b100111011 /
b100 .
0"
b1001101 $
b1001101 (
b1001101 -
b1001101 0
#785000
b0 +
b100111011 !
b100111011 ,
1"
#790000
b10 )
b10010000 *
b10010000 /
b100 .
0"
b1001110 $
b1001110 (
b1001110 -
b1001110 0
#795000
b100 +
b1001101111 !
b1001101111 ,
1"
#800000
b110 )
b1101111 *
b1101111 /
b101 .
0"
b1001111 $
b1001111 (
b1001111 -
b1001111 0
#805000
b0 +
b1010010000 !
b1010010000 ,
1"
#810000
b10 )
b100110000 *
b100110000 /
b10 .
0"
b1010000 $
b1010000 (
b1010000 -
b1010000 0
#815000
b11100 +
b100110000 !
b100110000 ,
1"
#820000
b110 )
b111001111 *
b111001111 /
b11 .
0"
b1010001 $
b1010001 (
b1010001 -
b1010001 0
#825000
b0 +
b111001111 !
b111001111 ,
1"
#830000
b101 )
b111001110 *
b111001110 /
b11 .
0"
b1010010 $
b1010010 (
b1010010 -
b1010010 0
#835000
b10 +
b111001110 !
b111001110 ,
1"
#840000
b11 )
b100110001 *
b100110001 /
b100 .
0"
b1010011 $
b1010011 (
b1010011 -
b1010011 0
#845000
b0 +
b100110001 !
b100110001 ,
1"
#850000
b100 )
b111001100 *
b111001100 /
b11 .
0"
b1010100 $
b1010100 (
b1010100 -
b1010100 0
#855000
b111001100 !
b111001100 ,
1"
#860000
b100 )
b100110011 *
b100110011 /
b100 .
0"
b1010101 $
b1010101 (
b1010101 -
b1010101 0
#865000
b100110011 !
b100110011 ,
1"
#870000
b11 )
b10011000 *
b10011000 /
b100 .
0"
b1010110 $
b1010110 (
b1010110 -
b1010110 0
#875000
b10 +
b1001100111 !
b1001100111 ,
1"
#880000
b101 )
b1100111 *
b1100111 /
b101 .
0"
b1010111 $
b1010111 (
b1010111 -
b1010111 0
#885000
b0 +
b1010011000 !
b1010011000 ,
1"
#890000
b11 )
b111001000 *
b111001000 /
b11 .
0"
b1011000 $
b1011000 (
b1011000 -
b1011000 0
#895000
b11110 +
b111001000 !
b111001000 ,
1"
#900000
b101 )
b100110111 *
b100110111 /
b100 .
0"
b1011001 $
b1011001 (
b1011001 -
b1011001 0
#905000
b0 +
b100110111 !
b100110111 ,
1"
#910000
b100 )
b10011100 *
b10011100 /
b100 .
0"
b1011010 $
b1011010 (
b1011010 -
b1011010 0
#915000
b1001100011 !
b1001100011 ,
1"
#920000
b100 )
b1100011 *
b1100011 /
b101 .
0"
b1011011 $
b1011011 (
b1011011 -
b1011011 0
#925000
b1010011100 !
b1010011100 ,
1"
#930000
b101 )
b10011110 *
b10011110 /
b100 .
0"
b1011100 $
b1011100 (
b1011100 -
b1011100 0
#935000
b11110 +
b1001100001 !
b1001100001 ,
1"
#940000
b11 )
b1100001 *
b1100001 /
b101 .
0"
b1011101 $
b1011101 (
b1011101 -
b1011101 0
#945000
b0 +
b1010011110 !
b1010011110 ,
1"
#950000
b10 )
b1100000 *
b1100000 /
b101 .
0"
b1011110 $
b1011110 (
b1011110 -
b1011110 0
#955000
b100 +
b1010011111 !
b1010011111 ,
1"
#960000
b110 )
b10011111 *
b10011111 /
b110 .
0"
b1011111 $
b1011111 (
b1011111 -
b1011111 0
#965000
b0 +
b1001100000 !
b1001100000 ,
1"
#970000
b1 )
b100100000 *
b100100000 /
b10 .
0"
b1100000 $
b1100000 (
b1100000 -
b1100000 0
#975000
b11010 +
b100100000 !
b100100000 ,
1"
#980000
b111 )
b111011111 *
b111011111 /
b11 .
0"
b1100001 $
b1100001 (
b1100001 -
b1100001 0
#985000
b0 +
b111011111 !
b111011111 ,
1"
#990000
b110 )
b111011110 *
b111011110 /
b11 .
0"
b1100010 $
b1100010 (
b1100010 -
b1100010 0
#995000
b100 +
b111011110 !
b111011110 ,
1"
#1000000
b10 )
b100100001 *
b100100001 /
b100 .
0"
b1100011 $
b1100011 (
b1100011 -
b1100011 0
#1005000
b0 +
b100100001 !
b100100001 ,
1"
#1010000
b101 )
b111011100 *
b111011100 /
b11 .
0"
b1100100 $
b1100100 (
b1100100 -
b1100100 0
#1015000
b10 +
b111011100 !
b111011100 ,
1"
#1020000
b11 )
b100100011 *
b100100011 /
b100 .
0"
b1100101 $
b1100101 (
b1100101 -
b1100101 0
#1025000
b0 +
b100100011 !
b100100011 ,
1"
#1030000
b10 )
b10001000 *
b10001000 /
b100 .
0"
b1100110 $
b1100110 (
b1100110 -
b1100110 0
#1035000
b100 +
b1001110111 !
b1001110111 ,
1"
#1040000
b110 )
b1110111 *
b1110111 /
b101 .
0"
b1100111 $
b1100111 (
b1100111 -
b1100111 0
#1045000
b0 +
b1010001000 !
b1010001000 ,
1"
#1050000
b100 )
b111011000 *
b111011000 /
b11 .
0"
b1101000 $
b1101000 (
b1101000 -
b1101000 0
#1055000
b111011000 !
b111011000 ,
1"
#1060000
b100 )
b100100111 *
b100100111 /
b100 .
0"
b1101001 $
b1101001 (
b1101001 -
b1101001 0
#1065000
b100100111 !
b100100111 ,
1"
#1070000
b11 )
b10001100 *
b10001100 /
b100 .
0"
b1101010 $
b1101010 (
b1101010 -
b1101010 0
#1075000
b10 +
b1001110011 !
b1001110011 ,
1"
#1080000
b101 )
b1110011 *
b1110011 /
b101 .
0"
b1101011 $
b1101011 (
b1101011 -
b1101011 0
#1085000
b0 +
b1010001100 !
b1010001100 ,
1"
#1090000
b100 )
b10001110 *
b10001110 /
b100 .
0"
b1101100 $
b1101100 (
b1101100 -
b1101100 0
#1095000
b1001110001 !
b1001110001 ,
1"
#1100000
b100 )
b1110001 *
b1110001 /
b101 .
0"
b1101101 $
b1101101 (
b1101101 -
b1101101 0
#1105000
b1010001110 !
b1010001110 ,
1"
#1110000
b11 )
b1110000 *
b1110000 /
b101 .
0"
b1101110 $
b1101110 (
b1101110 -
b1101110 0
#1115000
b10 +
b1010001111 !
b1010001111 ,
1"
#1120000
b101 )
b10001111 *
b10001111 /
b110 .
0"
b1101111 $
b1101111 (
b1101111 -
b1101111 0
#1125000
b0 +
b1001110000 !
b1001110000 ,
1"
#1130000
b11 )
b111010000 *
b111010000 /
b11 .
0"
b1110000 $
b1110000 (
b1110000 -
b1110000 0
#1135000
b11110 +
b111010000 !
b111010000 ,
1"
#1140000
b101 )
b100101111 *
b100101111 /
b100 .
0"
b1110001 $
b1110001 (
b1110001 -
b1110001 0
#1145000
b0 +
b100101111 !
b100101111 ,
1"
#1150000
b10 )
b10000100 *
b10000100 /
b100 .
0"
b1110010 $
b1110010 (
b1110010 -
b1110010 0
#1155000
b100 +
b1001111011 !
b1001111011 ,
1"
#1160000
b110 )
b1111011 *
b1111011 /
b101 .
0"
b1110011 $
b1110011 (
b1110011 -
b1110011 0
#1165000
b0 +
b1010000100 !
b1010000100 ,
1"
#1170000
b11 )
b10000110 *
b10000110 /
b100 .
0"
b1110100 $
b1110100 (
b1110100 -
b1110100 0
#1175000
b10 +
b1001111001 !
b1001111001 ,
1"
#1180000
b101 )
b1111001 *
b1111001 /
b101 .
0"
b1110101 $
b1110101 (
b1110101 -
b1110101 0
#1185000
b0 +
b1010000110 !
b1010000110 ,
1"
#1190000
b100 )
b1111000 *
b1111000 /
b101 .
0"
b1110110 $
b1110110 (
b1110110 -
b1110110 0
#1195000
b1010000111 !
b1010000111 ,
1"
#1200000
b100 )
b10000111 *
b10000111 /
b110 .
0"
b1110111 $
b1110111 (
b1110111 -
b1110111 0
#1205000
b1001111000 !
b1001111000 ,
1"
#1210000
b10 )
b10000010 *
b10000010 /
b100 .
0"
b1111000 $
b1111000 (
b1111000 -
b1111000 0
#1215000
b100 +
b1001111101 !
b1001111101 ,
1"
#1220000
b110 )
b1111101 *
b1111101 /
b101 .
0"
b1111001 $
b1111001 (
b1111001 -
b1111001 0
#1225000
b0 +
b1010000010 !
b1010000010 ,
1"
#1230000
b101 )
b1111100 *
b1111100 /
b101 .
0"
b1111010 $
b1111010 (
b1111010 -
b1111010 0
#1235000
b11110 +
b1010000011 !
b1010000011 ,
1"
#1240000
b11 )
b10000011 *
b10000011 /
b110 .
0"
b1111011 $
b1111011 (
b1111011 -
b1111011 0
#1245000
b0 +
b1001111100 !
b1001111100 ,
1"
#1250000
b110 )
b1111110 *
b1111110 /
b101 .
0"
b1111100 $
b1111100 (
b1111100 -
b1111100 0
#1255000
b11100 +
b1010000001 !
b1010000001 ,
1"
#1260000
b10 )
b10000001 *
b10000001 /
b110 .
0"
b1111101 $
b1111101 (
b1111101 -
b1111101 0
#1265000
b0 +
b1001111110 !
b1001111110 ,
1"
#1270000
b1 )
b10000000 *
b10000000 /
b110 .
0"
b1111110 $
b1111110 (
b1111110 -
b1111110 0
#1275000
b110 +
b1001111111 !
b1001111111 ,
1"
#1280000
b111 )
b1111111 *
b1111111 /
b111 .
0"
b1111111 $
b1111111 (
b1111111 -
b1111111 0
#1285000
b0 +
b1010000000 !
b1010000000 ,
1"
#1290000
b1 )
b110000000 *
b110000000 /
b1 .
0"
b10000000 $
b10000000 (
b10000000 -
b10000000 0
#1295000
b11010 +
b110000000 !
b110000000 ,
1"
#1300000
b111 )
b101111111 *
b101111111 /
b10 .
0"
b10000001 $
b10000001 (
b10000001 -
b10000001 0
#1305000
b0 +
b101111111 !
b101111111 ,
1"
#1310000
b110 )
b101111110 *
b101111110 /
b10 .
0"
b10000010 $
b10000010 (
b10000010 -
b10000010 0
#1315000
b100 +
b101111110 !
b101111110 ,
1"
#1320000
b10 )
b110000001 *
b110000001 /
b11 .
0"
b10000011 $
b10000011 (
b10000011 -
b10000011 0
#1325000
b0 +
b110000001 !
b110000001 ,
1"
#1330000
b101 )
b101111100 *
b101111100 /
b10 .
0"
b10000100 $
b10000100 (
b10000100 -
b10000100 0
#1335000
b10 +
b101111100 !
b101111100 ,
1"
#1340000
b11 )
b110000011 *
b110000011 /
b11 .
0"
b10000101 $
b10000101 (
b10000101 -
b10000101 0
#1345000
b0 +
b110000011 !
b110000011 ,
1"
#1350000
b10 )
b110000010 *
b110000010 /
b11 .
0"
b10000110 $
b10000110 (
b10000110 -
b10000110 0
#1355000
b11100 +
b110000010 !
b110000010 ,
1"
#1360000
b110 )
b101111101 *
b101111101 /
b100 .
0"
b10000111 $
b10000111 (
b10000111 -
b10000111 0
#1365000
b0 +
b101111101 !
b101111101 ,
1"
#1370000
b100 )
b101111000 *
b101111000 /
b10 .
0"
b10001000 $
b10001000 (
b10001000 -
b10001000 0
#1375000
b101111000 !
b101111000 ,
1"
#1380000
b100 )
b110000111 *
b110000111 /
b11 .
0"
b10001001 $
b10001001 (
b10001001 -
b10001001 0
#1385000
b110000111 !
b110000111 ,
1"
#1390000
b11 )
b110000110 *
b110000110 /
b11 .
0"
b10001010 $
b10001010 (
b10001010 -
b10001010 0
#1395000
b11110 +
b110000110 !
b110000110 ,
1"
